ecmanalysis/ST.py
ecmanalysis/__init__.py
ecmanalysis-0.0.18.dist-info/METADATA
ecmanalysis-0.0.18.dist-info/WHEEL
ecmanalysis-0.0.18.dist-info/top_level.txt
ecmanalysis-0.0.18.dist-info/RECORD
