Metadata-Version: 2.1
Name: ecmanalysis
Version: 0.0.18
Summary: Tools for analysis of the extracellular matrix
Home-page: UNKNOWN
Author: Mohamed Ghafoor
Author-email: <moeghaf@gmail.com>
License: UNKNOWN
Keywords: extracellular matrix,matrisome,spatial transcriptomics
Platform: UNKNOWN
Classifier: Development Status :: 1 - Planning
Classifier: Intended Audience :: Developers
Classifier: Programming Language :: Python :: 3
Classifier: Operating System :: Unix
Classifier: Operating System :: MacOS :: MacOS X
Classifier: Operating System :: Microsoft :: Windows
Requires-Dist: scanpy
Requires-Dist: bbknn
Requires-Dist: anndata
Requires-Dist: pandas
Requires-Dist: numpy
Requires-Dist: matplotlib
Requires-Dist: seaborn
Requires-Dist: scikit-learn
Requires-Dist: yellowbrick
Requires-Dist: requests
